MANIFEST.in
README.md
setup.py
realex/__init__.py
realex/realex.py
realex.egg-info/PKG-INFO
realex.egg-info/SOURCES.txt
realex.egg-info/dependency_links.txt
realex.egg-info/not-zip-safe
realex.egg-info/top_level.txt
realex/realex_files/3ds_verify_enrolled.xml
realex/realex_files/3ds_verify_signed.xml
realex/realex_files/auth.xml