Metadata-Version: 1.0
Name: realex
Version: 0.3
Summary: Integrated example application using Realexs Auth API
Home-page: https://github.com/TestingPays
Author: Luke Rickard
Author-email: luke.rickard@thepayment.works
License: MIT
Platform: UNKNOWN
